{"基于 G1-CRITIC 的输水管线工程盾构施工风险模糊评价": "https://mp.weixin.qq.com/s/sEPlV90w1XvaAmjlvUSfPw",
   "【书摘】创业团队需要4种人": "https://mp.weixin.qq.com/s/ma6uod7Q1MFGHLFbYKGWzA",
    "【书摘】建立信任": "https://mp.weixin.qq.com/s/udkMgaKf7hD8MGifFKqSlA",
    "【back to school】如何成功管理项目": "https://mp.weixin.qq.com/s/VRWSiW6WSqi_LGH1t9lPuA",
    "【读书】分包合同索赔及争端": "https://mp.weixin.qq.com/s/Qvbrs4MpMo35xNA4AKfF8Q",
    "【PMP】每日一题-2018-8-31": "https://mp.weixin.qq.com/s/5cmgJ1Qhlw6LHv-VWCcFTQ",
    "【back to school】沟通的障碍——主观障碍（上）": "https://mp.weixin.qq.com/s/RwBfluvf4k5NJvuufD189Q",
    "【PMP】每日一题-2018-10-21": "https://mp.weixin.qq.com/s/mPpsv39CIO9iGGTvZffv3w",
    "【back to school】如何有效沟通——主动倾听": "https://mp.weixin.qq.com/s/yjYWULCQRuoATr9hQbYX7A",
    "【读书】突发事件现场应急处置措施——损伤事故": "https://mp.weixin.qq.com/s/GJu2lxdzbwnh8yuBLwuynw"
}